{"v":4,"entries":{"hooks-useautoplayaudiotrack--docs":{"id":"hooks-useautoplayaudiotrack--docs","title":"hooks/useAutoPlayAudioTrack","name":"Docs","importPath":"./src/stories/hooks/useAutoPlayAudioTrack.en-US.mdx","storiesImports":[],"type":"docs","tags":["unattached-mdx","docs"]},"hooks-useautoplayvideotrack--docs":{"id":"hooks-useautoplayvideotrack--docs","title":"hooks/useAutoPlayVideoTrack","name":"Docs","importPath":"./src/stories/hooks/useAutoPlayVideoTrack.en-US.mdx","storiesImports":[],"type":"docs","tags":["unattached-mdx","docs"]},"hooks-useconnectionstate--docs":{"id":"hooks-useconnectionstate--docs","title":"hooks/useConnectionState","name":"Docs","importPath":"./src/stories/hooks/useConnectionState.en-US.mdx","storiesImports":[],"type":"docs","tags":["unattached-mdx","docs"]},"hooks-usecurrentuid--docs":{"id":"hooks-usecurrentuid--docs","title":"hooks/useCurrentUID","name":"Docs","importPath":"./src/stories/hooks/useCurrentUID.en-US.mdx","storiesImports":[],"type":"docs","tags":["unattached-mdx","docs"]},"hooks-useisconnected--docs":{"id":"hooks-useisconnected--docs","title":"hooks/useIsConnected","name":"Docs","importPath":"./src/stories/hooks/useIsConnected.en-US.mdx","storiesImports":[],"type":"docs","tags":["unattached-mdx","docs"]},"hooks-usejoin--docs":{"id":"hooks-usejoin--docs","title":"hooks/useJoin","name":"Docs","importPath":"./src/stories/hooks/useJoin.en-US.mdx","storiesImports":[],"type":"docs","tags":["unattached-mdx","docs"]},"hooks-uselocalcameratrack--docs":{"id":"hooks-uselocalcameratrack--docs","title":"hooks/useLocalCameraTrack","name":"Docs","importPath":"./src/stories/hooks/useLocalCameraTrack.en-US.mdx","storiesImports":[],"type":"docs","tags":["unattached-mdx","docs"]},"hooks-uselocalmicrophonetrack--docs":{"id":"hooks-uselocalmicrophonetrack--docs","title":"hooks/useLocalMicrophoneTrack","name":"Docs","importPath":"./src/stories/hooks/useLocalMicrophoneTrack.en-US.mdx","storiesImports":[],"type":"docs","tags":["unattached-mdx","docs"]},"hooks-usenetworkquality--docs":{"id":"hooks-usenetworkquality--docs","title":"hooks/useNetworkQuality","name":"Docs","importPath":"./src/stories/hooks/useNetworkQuality.en-US.mdx","storiesImports":[],"type":"docs","tags":["unattached-mdx","docs"]},"hooks-usepublish--docs":{"id":"hooks-usepublish--docs","title":"hooks/usePublish","name":"Docs","importPath":"./src/stories/hooks/usePublish.en-US.mdx","storiesImports":[],"type":"docs","tags":["unattached-mdx","docs"]},"hooks-usertcclient--docs":{"id":"hooks-usertcclient--docs","title":"hooks/useRTCClient","name":"Docs","importPath":"./src/stories/hooks/useRTCClient.en-US.mdx","storiesImports":[],"type":"docs","tags":["unattached-mdx","docs"]},"hooks-useremoteaudiotracks--docs":{"id":"hooks-useremoteaudiotracks--docs","title":"hooks/useRemoteAudioTracks","name":"Docs","importPath":"./src/stories/hooks/useRemoteAudioTracks.en-US.mdx","storiesImports":[],"type":"docs","tags":["unattached-mdx","docs"]},"hooks-useremoteusertrack--docs":{"id":"hooks-useremoteusertrack--docs","title":"hooks/useRemoteUserTrack","name":"Docs","importPath":"./src/stories/hooks/useRemoteUserTrack.en-US.mdx","storiesImports":[],"type":"docs","tags":["unattached-mdx","docs"]},"hooks-useremoteusers--docs":{"id":"hooks-useremoteusers--docs","title":"hooks/useRemoteUsers","name":"Docs","importPath":"./src/stories/hooks/useRemoteUsers.en-US.mdx","storiesImports":[],"type":"docs","tags":["unattached-mdx","docs"]},"hooks-useremotevideotracks--docs":{"id":"hooks-useremotevideotracks--docs","title":"hooks/useRemoteVideoTracks","name":"Docs","importPath":"./src/stories/hooks/useRemoteVideoTracks.en-US.mdx","storiesImports":[],"type":"docs","tags":["unattached-mdx","docs"]},"hooks-usevolumelevel--docs":{"id":"hooks-usevolumelevel--docs","title":"hooks/useVolumeLevel","name":"Docs","importPath":"./src/stories/hooks/useVolumeLevel.en-US.mdx","storiesImports":[],"type":"docs","tags":["unattached-mdx","docs"]},"track-localaudiotrack--docs":{"id":"track-localaudiotrack--docs","title":"Track/LocalAudioTrack","name":"Docs","importPath":"./src/stories/LocalAudioTrack.stories.tsx","type":"docs","tags":["autodocs","docs"],"storiesImports":[]},"track-localaudiotrack--enabled":{"id":"track-localaudiotrack--enabled","title":"Track/LocalAudioTrack","name":"Enabled","importPath":"./src/stories/LocalAudioTrack.stories.tsx","tags":["autodocs","story"],"type":"story"},"track-localaudiotrack--empty-track":{"id":"track-localaudiotrack--empty-track","title":"Track/LocalAudioTrack","name":"Empty Track","importPath":"./src/stories/LocalAudioTrack.stories.tsx","tags":["autodocs","story"],"type":"story"},"user-localuser--docs":{"id":"user-localuser--docs","title":"User/LocalUser","name":"Docs","importPath":"./src/stories/LocalUser.stories.tsx","type":"docs","tags":["autodocs","docs"],"storiesImports":[]},"user-localuser--overview":{"id":"user-localuser--overview","title":"User/LocalUser","name":"Overview","importPath":"./src/stories/LocalUser.stories.tsx","tags":["autodocs","story"],"type":"story"},"track-localvideotrack--docs":{"id":"track-localvideotrack--docs","title":"Track/LocalVideoTrack","name":"Docs","importPath":"./src/stories/LocalVideoTrack.stories.tsx","type":"docs","tags":["autodocs","docs"],"storiesImports":[]},"track-localvideotrack--enabled":{"id":"track-localvideotrack--enabled","title":"Track/LocalVideoTrack","name":"Enabled","importPath":"./src/stories/LocalVideoTrack.stories.tsx","tags":["autodocs","story"],"type":"story"},"track-localvideotrack--empty-track":{"id":"track-localvideotrack--empty-track","title":"Track/LocalVideoTrack","name":"Empty Track","importPath":"./src/stories/LocalVideoTrack.stories.tsx","tags":["autodocs","story"],"type":"story"},"track-remoteaudiotrack--docs":{"id":"track-remoteaudiotrack--docs","title":"Track/RemoteAudioTrack","name":"Docs","importPath":"./src/stories/RemoteAudioTrack.stories.tsx","type":"docs","tags":["autodocs","docs"],"storiesImports":[]},"track-remoteaudiotrack--enabled":{"id":"track-remoteaudiotrack--enabled","title":"Track/RemoteAudioTrack","name":"Enabled","importPath":"./src/stories/RemoteAudioTrack.stories.tsx","tags":["autodocs","story"],"type":"story"},"track-remoteaudiotrack--empty-track":{"id":"track-remoteaudiotrack--empty-track","title":"Track/RemoteAudioTrack","name":"Empty Track","importPath":"./src/stories/RemoteAudioTrack.stories.tsx","tags":["autodocs","story"],"type":"story"},"user-remoteuser--docs":{"id":"user-remoteuser--docs","title":"User/RemoteUser","name":"Docs","importPath":"./src/stories/RemoteUser.stories.tsx","type":"docs","tags":["autodocs","docs"],"storiesImports":[]},"user-remoteuser--overview":{"id":"user-remoteuser--overview","title":"User/RemoteUser","name":"Overview","importPath":"./src/stories/RemoteUser.stories.tsx","tags":["autodocs","story"],"type":"story"},"user-remoteuser--with-cover":{"id":"user-remoteuser--with-cover","title":"User/RemoteUser","name":"With Cover","importPath":"./src/stories/RemoteUser.stories.tsx","tags":["autodocs","story"],"type":"story"},"user-remoteuser--with-controls":{"id":"user-remoteuser--with-controls","title":"User/RemoteUser","name":"With Controls","importPath":"./src/stories/RemoteUser.stories.tsx","tags":["autodocs","story"],"type":"story"},"track-remotevideotrack--docs":{"id":"track-remotevideotrack--docs","title":"Track/RemoteVideoTrack","name":"Docs","importPath":"./src/stories/RemoteVideoTrack.stories.tsx","type":"docs","tags":["autodocs","docs"],"storiesImports":[]},"track-remotevideotrack--enabled":{"id":"track-remotevideotrack--enabled","title":"Track/RemoteVideoTrack","name":"Enabled","importPath":"./src/stories/RemoteVideoTrack.stories.tsx","tags":["autodocs","story"],"type":"story"},"track-remotevideotrack--empty-track":{"id":"track-remotevideotrack--empty-track","title":"Track/RemoteVideoTrack","name":"Empty Track","importPath":"./src/stories/RemoteVideoTrack.stories.tsx","tags":["autodocs","story"],"type":"story"},"tools-trackboundary--docs":{"id":"tools-trackboundary--docs","title":"Tools/TrackBoundary","name":"Docs","importPath":"./src/stories/TrackBoundary.stories.tsx","type":"docs","tags":["autodocs","docs"],"storiesImports":[]},"tools-trackboundary--layout-switch-with-track-boundary":{"id":"tools-trackboundary--layout-switch-with-track-boundary","title":"Tools/TrackBoundary","name":"Layout Switch With Track Boundary","importPath":"./src/stories/TrackBoundary.stories.tsx","tags":["autodocs","story"],"type":"story"},"tools-trackboundary--layout-switch-without-track-boundary":{"id":"tools-trackboundary--layout-switch-without-track-boundary","title":"Tools/TrackBoundary","name":"Layout Switch Without Track Boundary","importPath":"./src/stories/TrackBoundary.stories.tsx","tags":["autodocs","story"],"type":"story"}}}
